hybrid_agent_mcp_server/__init__.py
hybrid_agent_mcp_server/main.py
hybrid_agent_mcp_server-0.1.3.dist-info/METADATA
hybrid_agent_mcp_server-0.1.3.dist-info/WHEEL
hybrid_agent_mcp_server-0.1.3.dist-info/entry_points.txt
hybrid_agent_mcp_server-0.1.3.dist-info/top_level.txt
hybrid_agent_mcp_server-0.1.3.dist-info/RECORD
