Metadata-Version: 2.4
Name: hybrid-agent-mcp-server
Version: 0.1.3
Summary: MCP Server for Hybrid Agent Environment Management
Author: Ki
Requires-Python: >=3.8
Requires-Dist: mcp
Dynamic: author
Dynamic: requires-dist
Dynamic: requires-python
Dynamic: summary
